Metadata-Version: 1.1
Name: booby
Version: 0.7.0
Summary: Data modeling and validation Python library
Home-page: https://github.com/jaimegildesagredo/booby
Author: Jaime Gil de Sagredo Luna
Author-email: jaimegildesagredo@gmail.com
License: UNKNOWN
Platform: UNKNOWN
Classifier: Development Status :: 3 - Alpha
Classifier: Intended Audience :: Developers
Classifier: Natural Language :: English
Classifier: Operating System :: OS Independent
Classifier: Programming Language :: Python
Classifier: Programming Language :: Python :: 2.7
Classifier: Programming Language :: Python :: 3.3
Classifier: Topic :: Software Development :: Libraries :: Python Modules
